retsim_pytorch/__about__.py
retsim_pytorch/__init__.py
retsim_pytorch/retsim.py
retsim_pytorch/converter/__init__.py
retsim_pytorch/converter/retsim_converter.py
retsim_pytorch/modules/__init__.py
retsim_pytorch/modules/activations.py
retsim_pytorch/modules/gau.py
retsim_pytorch/modules/metric_embedding.py
retsim_pytorch/modules/norm.py
retsim_pytorch/modules/pooling.py
retsim_pytorch/modules/positional_embeddings.py
retsim_pytorch/preprocessing/__init__.py
retsim_pytorch/preprocessing/binarizer.py
retsim_pytorch-0.1.1.dist-info/METADATA
retsim_pytorch-0.1.1.dist-info/WHEEL
retsim_pytorch-0.1.1.dist-info/licenses/LICENSE
retsim_pytorch-0.1.1.dist-info/RECORD
