Metadata-Version: 2.3
Name: retsim-pytorch
Version: 0.1.1
Project-URL: Documentation, https://github.com/LLukas22/retsim-pytorch#readme
Project-URL: Issues, https://github.com/LLukas22/retsim-pytorch/issues
Project-URL: Source, https://github.com/LLukas22/retsim-pytorch
Author-email: Lukas Kreussel <65088241+LLukas22@users.noreply.github.com>
License-Expression: MIT
License-File: LICENSE
Classifier: Development Status :: 4 - Beta
Classifier: Programming Language :: Python
Classifier: Programming Language :: Python :: 3.8
Classifier: Programming Language :: Python :: 3.9
Classifier: Programming Language :: Python :: 3.10
Classifier: Programming Language :: Python :: 3.11
Classifier: Programming Language :: Python :: 3.12
Classifier: Programming Language :: Python :: Implementation :: CPython
Classifier: Programming Language :: Python :: Implementation :: PyPy
Requires-Python: >=3.8
Requires-Dist: torch>=2.0.0
Provides-Extra: convert
Requires-Dist: keras==2.15.0; extra == 'convert'
Requires-Dist: safetensors==0.4.2; extra == 'convert'
Requires-Dist: tensorflow==2.15.0; extra == 'convert'
Provides-Extra: test
Requires-Dist: keras==2.15.0; extra == 'test'
Requires-Dist: onnxruntime==1.17.1; extra == 'test'
Requires-Dist: pytest>=8.0.0; extra == 'test'
Requires-Dist: retvec==1.0.1; extra == 'test'
Requires-Dist: safetensors==0.4.2; extra == 'test'
Requires-Dist: tensorflow-similarity==0.17.1; extra == 'test'
Requires-Dist: tensorflow==2.15.0; extra == 'test'
